mortal_shell/__init__.py
mortal_shell/shell_main.cpython-37m-x86_64-linux-gnu.so
mortal_shell-4.1.0.dist-info/METADATA
mortal_shell-4.1.0.dist-info/WHEEL
mortal_shell-4.1.0.dist-info/top_level.txt
mortal_shell-4.1.0.dist-info/RECORD
