Metadata-Version: 2.1
Name: mortal-shell
Version: 4.1.0
Summary: mortal工具集::shell
Home-page: https://www.example.com
Author: Mortal
Author-email: mortal9098@163.com
License: MIT
Classifier: Development Status :: 4 - Beta
Classifier: Programming Language :: Python :: 3
Classifier: Programming Language :: Python :: 3.7
Classifier: Operating System :: POSIX :: Linux
Classifier: Intended Audience :: Developers
Requires-Python: >=3.7
Requires-Dist: mortal-bases
Requires-Dist: mortal-var
Requires-Dist: mortal-log
Requires-Dist: mortal-ssh
Requires-Dist: paramiko
